liontk/__init__.py
liontk/gui.py
liontk/init.py
liontk/symbols.py
liontk/tcltalk.py
liontk-2022.1.22.dist-info/METADATA
liontk-2022.1.22.dist-info/WHEEL
liontk-2022.1.22.dist-info/top_level.txt
liontk-2022.1.22.dist-info/RECORD
